data_plumber/__init__.py
data_plumber/array.py
data_plumber/component.py
data_plumber/context.py
data_plumber/error.py
data_plumber/fork.py
data_plumber/output.py
data_plumber/pipeline.py
data_plumber/py.typed
data_plumber/ref.py
data_plumber/stage.py
data_plumber-1.15.0.dist-info/LICENSE
data_plumber-1.15.0.dist-info/METADATA
data_plumber-1.15.0.dist-info/WHEEL
data_plumber-1.15.0.dist-info/top_level.txt
data_plumber-1.15.0.dist-info/RECORD
