Metadata-Version: 2.1
Name: data-plumber
Version: 1.15.0
Summary: lightweight but versatile python-framework for multi-stage information processing
Home-page: https://pypi.org/project/data-plumber/
Author: Steffen Richters-Finger
Author-email: srichters@uni-muenster.de
License: MIT
Project-URL: Source, https://github.com/RichtersFinger/data-plumber
Platform: UNKNOWN
Classifier: Development Status :: 5 - Production/Stable
Classifier: Intended Audience :: Developers
Classifier: Topic :: Software Development :: Libraries
Classifier: License :: OSI Approved :: MIT License
Classifier: Programming Language :: Python :: 3
Classifier: Programming Language :: Python :: 3.10
Classifier: Programming Language :: Python :: 3.11
Classifier: Programming Language :: Python :: 3.12
Requires-Python: >=3.10
License-File: LICENSE
Provides-Extra: tests
Requires-Dist: pytest-cov ==4.1 ; extra == 'tests'
Requires-Dist: pytest ==7.4 ; extra == 'tests'
